plot2html/__init__.py
plot2html/plot2html.py
plot2html-0.0.10.dist-info/LICENSE
plot2html-0.0.10.dist-info/METADATA
plot2html-0.0.10.dist-info/WHEEL
plot2html-0.0.10.dist-info/top_level.txt
plot2html-0.0.10.dist-info/RECORD
